biginsight/__init__.py
biginsight/core.py
biginsight-0.0.35.dist-info/LICENSE
biginsight-0.0.35.dist-info/METADATA
biginsight-0.0.35.dist-info/WHEEL
biginsight-0.0.35.dist-info/top_level.txt
biginsight-0.0.35.dist-info/RECORD
