Metadata-Version: 2.1
Name: biginsight
Version: 0.0.35
Summary: Understand your users on your platform
Author: Geottuse
Author-email: admin@geottuse.com
Classifier: Programming Language :: Python :: 3
Classifier: License :: OSI Approved :: MIT License
Classifier: Operating System :: OS Independent
Requires-Python: >=3.9
License-File: LICENSE
